docker_registry_client/AuthorizationService.py
docker_registry_client/DockerRegistryClient.py
docker_registry_client/Image.py
docker_registry_client/Repository.py
docker_registry_client/_BaseClient.py
docker_registry_client/__init__.py
docker_registry_client/manifest.py
graingert_drc-0.5.0.dist-info/DESCRIPTION.rst
graingert_drc-0.5.0.dist-info/METADATA
graingert_drc-0.5.0.dist-info/RECORD
graingert_drc-0.5.0.dist-info/WHEEL
graingert_drc-0.5.0.dist-info/metadata.json
graingert_drc-0.5.0.dist-info/top_level.txt
